zendesk_mcp_server/__init__.py
zendesk_mcp_server/server.py
zendesk_mcp_server/zendesk_client.py
zendesk_mcp_server-0.1.1.dist-info/METADATA
zendesk_mcp_server-0.1.1.dist-info/WHEEL
zendesk_mcp_server-0.1.1.dist-info/entry_points.txt
zendesk_mcp_server-0.1.1.dist-info/licenses/LICENSE
zendesk_mcp_server-0.1.1.dist-info/RECORD
